Workbook

Sheet Nike Dataset
A1: Invoice Date | B1: Retailer | C1: Region | D1: State | E1: Product | F1: Price per Unit | G1: Units Sold | H1: Sale Value | I1: Operating Profit | J1: Operating Margin | K1: Sales Method
A2: 44593 | B2: Amazon | C2: Midwest | D2: Ohio | E2: Women's Athletic Footwear | F2: 42.3 | G2: 1566 | H2: 66241.8 | I2: 27311.49 | J2: 0.4123 | K2: Outlet
A3: 44118 | B3: Foot Locker | C3: Northeast | D3: New York | E3: Women's Athletic Footwear | F3: 90.64 | G3: 104 | H3: 9426.56 | I3: 2794.03 | J3: 0.2964 | K3: In-store
A4: 44888 | B4: Amazon | C4: West | D4: Colorado | E4: Women's Street Footwear | F4: 63.38 | G4: 1830 | H4: 115985.4 | I4: 11865.31 | J4: 0.1023 | K4: Outlet
A5: 44179 | B5: Amazon | C5: Midwest | D5: Michigan | E5: Women's Athletic Footwear | F5: 42.27 | G5: 828 | H5: 34999.56 | I5: 4686.44 | J5: 0.1339 | K5: Online
A6: 44478 | B6: West Gear | C6: Northeast | D6: New Jersey | E6: Men's Street Footwear | F6: 39.46 | G6: 650 | H6: 25649 | I6: 10010.8 | J6: 0.3903 | K6: Online
A7: 44731 | B7: Foot Locker | C7: Southeast | D7: Florida | E7: Women's Apparel | F7: 122.77 | G7: 213 | H7: 26150.01 | I7: 10444.31 | J7: 0.3994 | K7: In-store
A8: 44021 | B8: Amazon | C8: Southwest | D8: Nevada | E8: Men's Athletic Footwear | F8: 55.14 | G8: 596 | H8: 32863.44 | I8: 11357.6 | J8: 0.3456 | K8: Online
A9: 44868 | B9: West Gear | C9: West | D9: Washington | E9: Women's Apparel | F9: 49.61 | G9: 827 | H9: 41027.47 | I9: 7979.84 | J9: 0.1945 | K9: In-store
A10: 44913 | B10: Target | C10: Southeast | D10: North Carolina | E10: Men's Street Footwear | F10: 128.62 | G10: 1698 | H10: 218396.76 | I10: 45950.68 | J10: 0.2104 | K10: In-store
A11: 44234 | B11: Amazon | C11: West | D11: Oregon | E11: Women's Apparel | F11: 77.48 | G11: 1922 | H11: 148916.56 | I11: 48397.88 | J11: 0.325 | K11: Online
A12: 43956 | B12: West Gear | C12: Southeast | D12: Tennessee | E12: Men's Athletic Footwear | F12: 100.15 | G12: 1888 | H12: 189083.2 | I12: 57519.11 | J12: 0.3042 | K12: Outlet
A13: 44291 | B13: Foot Locker | C13: West | D13: Colorado | E13: Men's Street Footwear | F13: 48.34 | G13: 377 | H13: 18224.18 | I13: 6874.16 | J13: 0.3772 | K13: In-store
... A301: 44169 | B301: Kohl's | C301: Northeast | D301: Massachusetts | E301: Men's Street Footwear | F301: 126.01 | G301: 1954 | H301: 246223.54 | I301: 109421.74 | J301: 0.4444 | K301: Outlet

Sheet Summary Dashboard
A1: Nike Sales – Summary Dashboard
A3: Total Sale Value | B3: Total Units Sold | C3: Total Orders | D3: Avg Operating Margin | E3: Avg Price per Unit
A4: =SUM('Nike Dataset'!H2:H301) | B4: =SUM('Nike Dataset'!G2:G301) | C4: =COUNTA('Nike Dataset'!A2:A301) | D4: =AVERAGE('Nike Dataset'!J2:J301) | E4: =AVERAGE('Nike Dataset'!F2:F301)
A6: Sales by Region | D6: Sales by Retailer
A7: Region | B7: Total Sale Value | D7: Retailer | E7: Total Sale Value
A8: Northeast | B8: =SUMIF('Nike Dataset'!C2:C301,A8,'Nike Dataset'!H2:H301) | D8: Foot Locker | E8: =SUMIF('Nike Dataset'!B2:B301,D8,'Nike Dataset'!H2:H301)
A9: Southeast | B9: =SUMIF('Nike Dataset'!C2:C301,A9,'Nike Dataset'!H2:H301) | D9: Amazon | E9: =SUMIF('Nike Dataset'!B2:B301,D9,'Nike Dataset'!H2:H301)
A10: Midwest | B10: =SUMIF('Nike Dataset'!C2:C301,A10,'Nike Dataset'!H2:H301) | D10: Sports Direct | E10: =SUMIF('Nike Dataset'!B2:B301,D10,'Nike Dataset'!H2:H301)
A11: Southwest | B11: =SUMIF('Nike Dataset'!C2:C301,A11,'Nike Dataset'!H2:H301) | D11: Walmart | E11: =SUMIF('Nike Dataset'!B2:B301,D11,'Nike Dataset'!H2:H301)
A12: West | B12: =SUMIF('Nike Dataset'!C2:C301,A12,'Nike Dataset'!H2:H301) | D12: West Gear | E12: =SUMIF('Nike Dataset'!B2:B301,D12,'Nike Dataset'!H2:H301)
A13: Grand Total | B13: =SUM(B8:B12) | D13: Kohl's | E13: =SUMIF('Nike Dataset'!B2:B301,D13,'Nike Dataset'!H2:H301)
D14: Target | E14: =SUMIF('Nike Dataset'!B2:B301,D14,'Nike Dataset'!H2:H301)
D15: Grand Total | E15: =SUM(E8:E14)

Sheet Product Analysis
A1: Nike Sales – Product Analysis
A2: Product | B2: Units Sold | C2: Sale Value | D2: Operating Profit | E2: Avg Margin
A3: Men's Street Footwear | B3: =SUMIF('Nike Dataset'!E2:E301,A3,'Nike Dataset'!G2:G301) | C3: =SUMIF('Nike Dataset'!E2:E301,A3,'Nike Dataset'!H2:H301) | D3: =SUMIF('Nike Dataset'!E2:E301,A3,'Nike Dataset'!I2:I301) | E3: =AVERAGEIF('Nike Dataset'!E2:E301,A3,'Nike Dataset'!J2:J301)
A4: Women's Athletic Footwear | B4: =SUMIF('Nike Dataset'!E2:E301,A4,'Nike Dataset'!G2:G301) | C4: =SUMIF('Nike Dataset'!E2:E301,A4,'Nike Dataset'!H2:H301) | D4: =SUMIF('Nike Dataset'!E2:E301,A4,'Nike Dataset'!I2:I301) | E4: =AVERAGEIF('Nike Dataset'!E2:E301,A4,'Nike Dataset'!J2:J301)
A5: Men's Athletic Footwear | B5: =SUMIF('Nike Dataset'!E2:E301,A5,'Nike Dataset'!G2:G301) | C5: =SUMIF('Nike Dataset'!E2:E301,A5,'Nike Dataset'!H2:H301) | D5: =SUMIF('Nike Dataset'!E2:E301,A5,'Nike Dataset'!I2:I301) | E5: =AVERAGEIF('Nike Dataset'!E2:E301,A5,'Nike Dataset'!J2:J301)
A6: Women's Street Footwear | B6: =SUMIF('Nike Dataset'!E2:E301,A6,'Nike Dataset'!G2:G301) | C6: =SUMIF('Nike Dataset'!E2:E301,A6,'Nike Dataset'!H2:H301) | D6: =SUMIF('Nike Dataset'!E2:E301,A6,'Nike Dataset'!I2:I301) | E6: =AVERAGEIF('Nike Dataset'!E2:E301,A6,'Nike Dataset'!J2:J301)
A7: Men's Apparel | B7: =SUMIF('Nike Dataset'!E2:E301,A7,'Nike Dataset'!G2:G301) | C7: =SUMIF('Nike Dataset'!E2:E301,A7,'Nike Dataset'!H2:H301) | D7: =SUMIF('Nike Dataset'!E2:E301,A7,'Nike Dataset'!I2:I301) | E7: =AVERAGEIF('Nike Dataset'!E2:E301,A7,'Nike Dataset'!J2:J301)
A8: Women's Apparel | B8: =SUMIF('Nike Dataset'!E2:E301,A8,'Nike Dataset'!G2:G301) | C8: =SUMIF('Nike Dataset'!E2:E301,A8,'Nike Dataset'!H2:H301) | D8: =SUMIF('Nike Dataset'!E2:E301,A8,'Nike Dataset'!I2:I301) | E8: =AVERAGEIF('Nike Dataset'!E2:E301,A8,'Nike Dataset'!J2:J301)
A9: Total | B9: =SUM(B3:B8) | C9: =SUM(C3:C8) | D9: =SUM(D3:D8) | E9: =AVERAGE(E3:E8)

Sheet Sales Method
A1: Nike Sales – Sales Method Breakdown
A2: Sales Method | B2: Total Sale Value | C2: Units Sold | D2: % of Total Sales
A3: In-store | B3: =SUMIF('Nike Dataset'!K2:K301,A3,'Nike Dataset'!H2:H301) | C3: =SUMIF('Nike Dataset'!K2:K301,A3,'Nike Dataset'!G2:G301) | D3: =B3/SUM(B3:B5)
A4: Online | B4: =SUMIF('Nike Dataset'!K2:K301,A4,'Nike Dataset'!H2:H301) | C4: =SUMIF('Nike Dataset'!K2:K301,A4,'Nike Dataset'!G2:G301) | D4: =B4/SUM(B3:B5)
A5: Outlet | B5: =SUMIF('Nike Dataset'!K2:K301,A5,'Nike Dataset'!H2:H301) | C5: =SUMIF('Nike Dataset'!K2:K301,A5,'Nike Dataset'!G2:G301) | D5: =B5/SUM(B3:B5)
