Workbook

Sheet Nike Dataset
A1: Retailer | B1: Product | C1: Region | D1: State | E1: Sales Method | F1: Units Sold | G1: Sale Value | H1: Invoice Date
A2: Foot Locker | B2: Men's Street Footwear | C2: Northeast | D2: New York | E2: In-store | F2: 1200 | G2: 85000 | H2: 2020-01-15
A3: Foot Locker | B3: Women's Apparel | C3: Northeast | D3: New York | E3: In-store | F3: 800 | G3: 48000 | H3: 2020-02-20
A4: Amazon | B4: Men's Athletic Footwear | C4: West | D4: California | E4: Online | F4: 2500 | G4: 175000 | H4: 2020-03-10
A5: Amazon | B5: Women's Street Footwear | C5: West | D5: California | E5: Online | F5: 1800 | G5: 126000 | H5: 2020-04-05
A6: Walmart | B6: Men's Apparel | C6: South | D6: Texas | E6: In-store | F6: 3200 | G6: 96000 | H6: 2020-05-18
A7: Walmart | B7: Women's Athletic Footwear | C7: South | D7: Texas | E7: In-store | F7: 1400 | G7: 98000 | H7: 2020-06-22
A8: Nike Direct | B8: Men's Street Footwear | C8: Midwest | D8: Illinois | E8: Online | F8: 900 | G8: 63000 | H8: 2020-07-11
A9: Nike Direct | B9: Women's Apparel | C9: Midwest | D9: Illinois | E9: Online | F9: 1100 | G9: 66000 | H9: 2020-08-30
A10: Sports Direct | B10: Men's Athletic Footwear | C10: Southeast | D10: Florida | E10: Outlet | F10: 600 | G10: 36000 | H10: 2020-09-14
A11: Sports Direct | B11: Women's Street Footwear | C11: Southeast | D11: Florida | E11: Outlet | F11: 750 | G11: 45000 | H11: 2020-10-08
A12: Foot Locker | B12: Men's Apparel | C12: Northeast | D12: Massachusetts | E12: In-store | F12: 950 | G12: 57000 | H12: 2020-11-25
A13: Amazon | B13: Women's Athletic Footwear | C13: West | D13: Washington | E13: Online | F13: 2100 | G13: 147000 | H13: 2020-12-01
... A25: Nike Direct | B25: Women's Athletic Footwear | C25: Northeast | D25: New Jersey | E25: Online | F25: 1450 | G25: 101500 | H25: 2021-12-24

Sheet Summary Data
A1: SUMMARY CALCULATIONS
A6: KPI | B6: Value | D6: Region | E6: Sale Value | F6: Units Sold | H6: Product | I6: Sale Value | K6: Retailer | L6: Sale Value | N6: Sales Method | O6: Sale Value | Q6: Year | R6: Sale Value
A7: Total Sale Value | B7: =SUM('Nike Dataset'!G2:G25) -> 2025500 | D7: Northeast | E7: =SUMIF('Nike Dataset'!C$2:C$25,D7,'Nike Dataset'!G$2:G$25) -> 365000 | F7: =SUMIF('Nike Dataset'!C$2:C$25,D7,'Nike Dataset'!F$2:F$25) -> 5450 | H7: Men's Street Footwear | I7: =SUMIF('Nike Dataset'!B$2:B$25,H7,'Nike Dataset'!G$2:G$25) -> 333500 | K7: Foot Locker | L7: =SUMIF('Nike Dataset'!A$2:A$25,K7,'Nike Dataset'!G$2:G$25) -> 319200 | N7: In-store | O7: =SUMIF('Nike Dataset'!E$2:E$25,N7,'Nike Dataset'!G$2:G$25) -> 863200 | Q7: 2020 | R7: =SUMPRODUCT((YEAR(DATEVALUE('Nike Dataset'!H$2:H$25))=Q7)*'Nike Dataset'!G$2:G$25) -> 1042000
A8: Total Units Sold | B8: =SUM('Nike Dataset'!F2:F25) -> 34550 | D8: West | E8: =SUMIF('Nike Dataset'!C$2:C$25,D8,'Nike Dataset'!G$2:G$25) -> 703500 | F8: =SUMIF('Nike Dataset'!C$2:C$25,D8,'Nike Dataset'!F$2:F$25) -> 11350 | H8: Women's Apparel | I8: =SUMIF('Nike Dataset'!B$2:B$25,H8,'Nike Dataset'!G$2:G$25) -> 232800 | K8: Amazon | L8: =SUMIF('Nike Dataset'!A$2:A$25,K8,'Nike Dataset'!G$2:G$25) -> 625500 | N8: Online | O8: =SUMIF('Nike Dataset'!E$2:E$25,N8,'Nike Dataset'!G$2:G$25) -> 1007500 | Q8: 2021 | R8: =SUMPRODUCT((YEAR(DATEVALUE('Nike Dataset'!H$2:H$25))=Q8)*'Nike Dataset'!G$2:G$25) -> 983500
A9: Total Orders | B9: =COUNTA('Nike Dataset'!A2:A25) -> 24 | D9: South | E9: =SUMIF('Nike Dataset'!C$2:C$25,D9,'Nike Dataset'!G$2:G$25) -> 544000 | F9: =SUMIF('Nike Dataset'!C$2:C$25,D9,'Nike Dataset'!F$2:F$25) -> 11200 | H9: Men's Athletic Footwear | I9: =SUMIF('Nike Dataset'!B$2:B$25,H9,'Nike Dataset'!G$2:G$25) -> 321000 | K9: Walmart | L9: =SUMIF('Nike Dataset'!A$2:A$25,K9,'Nike Dataset'!G$2:G$25) -> 544000 | N9: Outlet | O9: =SUMIF('Nike Dataset'!E$2:E$25,N9,'Nike Dataset'!G$2:G$25) -> 154800
A10: Avg Sale Value per Order | B10: =B7/B9 -> 84395.833 | D10: Midwest | E10: =SUMIF('Nike Dataset'!C$2:C$25,D10,'Nike Dataset'!G$2:G$25) -> 258200 | F10: =SUMIF('Nike Dataset'!C$2:C$25,D10,'Nike Dataset'!F$2:F$25) -> 3970 | H10: Women's Street Footwear | I10: =SUMIF('Nike Dataset'!B$2:B$25,H10,'Nike Dataset'!G$2:G$25) -> 342200 | K10: Nike Direct | L10: =SUMIF('Nike Dataset'!A$2:A$25,K10,'Nike Dataset'!G$2:G$25) -> 382000
A11: Avg Units per Order | B11: =B8/B9 -> 1439.5833 | D11: Southeast | E11: =SUMIF('Nike Dataset'!C$2:C$25,D11,'Nike Dataset'!G$2:G$25) -> 154800 | F11: =SUMIF('Nike Dataset'!C$2:C$25,D11,'Nike Dataset'!F$2:F$25) -> 2580 | H11: Men's Apparel | I11: =SUMIF('Nike Dataset'!B$2:B$25,H11,'Nike Dataset'!G$2:G$25) -> 295500 | K11: Sports Direct | L11: =SUMIF('Nike Dataset'!A$2:A$25,K11,'Nike Dataset'!G$2:G$25) -> 154800
H12: Women's Athletic Footwear | I12: =SUMIF('Nike Dataset'!B$2:B$25,H12,'Nike Dataset'!G$2:G$25) -> 500500

Sheet Dashboard - Page 1
B1: ⚡ NIKE SALES ANALYTICS DASHBOARD
B2: Sales Performance Overview | 2020 – 2021
B4: 💰 TOTAL SALE VALUE | D4: 📦 TOTAL UNITS SOLD | F4: 🛒 TOTAL ORDERS | H4: 🔽 FILTER SLICERS In Excel, use the Data tab → AutoFilter or Slicers on the Nike Dataset sheet to filter by: • Retailer • State • Sales Method • Year
B5: ='Summary Data'!B7 -> 2025500 | D5: ='Summary Data'!B8 -> 34550 | F5: ='Summary Data'!B9 -> 24
B8: ◆ CAPITAL BY REGION (Pie Chart) | F8: ◆ APPAREL PERFORMANCE (Bar Chart)
B35: ◆ GROWTH TRAJECTORY (Line Chart) | F35: ◆ RETAILER PERFORMANCE (Bar Chart)
B59: ◆ SALE METHOD SPLIT (Donut)

Sheet Dashboard - Page 2
B1: ⚡ NIKE SALES | GEOGRAPHIC & REGIONAL VIEW
B2: State & Region Breakdown | 2020 – 2021
B4: 💰 TOTAL SALE VALUE | D4: 📦 TOTAL UNITS SOLD | F4: 🛒 TOTAL ORDERS
B5: ='Summary Data'!B7 -> 2025500 | D5: ='Summary Data'!B8 -> 34550 | F5: ='Summary Data'!B9 -> 24
B8: ◆ SALES BY STATE & REGION
B9: State | C9: Region | D9: Sale Value | E9: Units Sold | F9: Sales Method
B10: New York | C10: Northeast | D10: =SUMIF('Nike Dataset'!D$2:D$25,B10,'Nike Dataset'!G$2:G$25) -> 133000 | E10: =SUMIF('Nike Dataset'!D$2:D$25,B10,'Nike Dataset'!F$2:F$25) -> 2000 | F10: In-store
B11: California | C11: West | D11: =SUMIF('Nike Dataset'!D$2:D$25,B11,'Nike Dataset'!G$2:G$25) -> 301000 | E11: =SUMIF('Nike Dataset'!D$2:D$25,B11,'Nike Dataset'!F$2:F$25) -> 4300 | F11: Online
B12: Texas | C12: South | D12: =SUMIF('Nike Dataset'!D$2:D$25,B12,'Nike Dataset'!G$2:G$25) -> 194000 | E12: =SUMIF('Nike Dataset'!D$2:D$25,B12,'Nike Dataset'!F$2:F$25) -> 4600 | F12: In-store
B13: Illinois | C13: Midwest | D13: =SUMIF('Nike Dataset'!D$2:D$25,B13,'Nike Dataset'!G$2:G$25) -> 129000 | E13: =SUMIF('Nike Dataset'!D$2:D$25,B13,'Nike Dataset'!F$2:F$25) -> 2000 | F13: Online
B14: Florida | C14: Southeast | D14: =SUMIF('Nike Dataset'!D$2:D$25,B14,'Nike Dataset'!G$2:G$25) -> 81000 | E14: =SUMIF('Nike Dataset'!D$2:D$25,B14,'Nike Dataset'!F$2:F$25) -> 1350 | F14: Outlet
B15: Massachusetts | C15: Northeast | D15: =SUMIF('Nike Dataset'!D$2:D$25,B15,'Nike Dataset'!G$2:G$25) -> 57000 | E15: =SUMIF('Nike Dataset'!D$2:D$25,B15,'Nike Dataset'!F$2:F$25) -> 950 | F15: In-store
B16: Washington | C16: West | D16: =SUMIF('Nike Dataset'!D$2:D$25,B16,'Nike Dataset'!G$2:G$25) -> 147000 | E16: =SUMIF('Nike Dataset'!D$2:D$25,B16,'Nike Dataset'!F$2:F$25) -> 2100 | F16: Online
B17: Georgia | C17: South | D17: =SUMIF('Nike Dataset'!D$2:D$25,B17,'Nike Dataset'!G$2:G$25) -> 112000 | E17: =SUMIF('Nike Dataset'!D$2:D$25,B17,'Nike Dataset'!F$2:F$25) -> 1600 | F17: In-store
B18: Oregon | C18: West | D18: =SUMIF('Nike Dataset'!D$2:D$25,B18,'Nike Dataset'!G$2:G$25) -> 78000 | E18: =SUMIF('Nike Dataset'!D$2:D$25,B18,'Nike Dataset'!F$2:F$25) -> 1300 | F18: Online
B19: North Carolina | C19: Southeast | D19: =SUMIF('Nike Dataset'!D$2:D$25,B19,'Nike Dataset'!G$2:G$25) -> 33000 | E19: =SUMIF('Nike Dataset'!D$2:D$25,B19,'Nike Dataset'!F$2:F$25) -> 550 | F19: Outlet
B20: Ohio | C20: Midwest | D20: =SUMIF('Nike Dataset'!D$2:D$25,B20,'Nike Dataset'!G$2:G$25) -> 52200 | E20: =SUMIF('Nike Dataset'!D$2:D$25,B20,'Nike Dataset'!F$2:F$25) -> 870 | F20: In-store
B21: Nevada | C21: West | D21: =SUMIF('Nike Dataset'!D$2:D$25,B21,'Nike Dataset'!G$2:G$25) -> 58500 | E21: =SUMIF('Nike Dataset'!D$2:D$25,B21,'Nike Dataset'!F$2:F$25) -> 1950 | F21: Online
... B28: New Jersey | C28: Northeast | D28: =SUMIF('Nike Dataset'!D$2:D$25,B28,'Nike Dataset'!G$2:G$25) -> 101500 | E28: =SUMIF('Nike Dataset'!D$2:D$25,B28,'Nike Dataset'!F$2:F$25) -> 1450 | F28: Online
H31: ◆ SALE VALUE BY REGION

Sheet 📋 How It Was Made
B1: HOW THIS DASHBOARD WAS BUILT (For Presentation Reference)
B3: SHEET | C3: PURPOSE
B4: Nike Dataset | C4: Raw data table with 24 rows — all sales transactions (Retailer, Product, Region, State, Sales Method, Units Sold, Sale Value, Invoice Date)
B5: Summary Data | C5: SUMIF / COUNTA formulas that aggregate the raw data by Region, Product, Retailer, Sales Method, and Year. Charts pull from here.
B6: Dashboard - Page 1 | C6: Main overview dashboard: KPI cards (Total Sale Value, Units Sold, Orders) + 5 charts (Pie by Region, Bar by Product, Line by Year, Bar by Retailer, Pie by Sales Method)
B7: Dashboard - Page 2 | C7: Geographic view: State-wise table with SUMIF formulas + Bar chart by Region. Mirrors the Power BI map page.
B9: VISUAL | C9: HOW IT WAS MADE
B10: KPI Cards | C10: Merged cells styled with dark fill + large bold font. Values pull from Summary Data sheet using = formula references.
B11: Pie Chart (Region) | C11: Insert → Chart → Pie. Data from Summary Data D7:E11. Shows % share of sale value per region.
B12: Bar Chart (Product) | C12: Insert → Chart → Column. Data from Summary Data H7:I12. X-axis = Products, Y-axis = Sale Value.
B13: Line Chart (Growth) | C13: Insert → Chart → Line. Data from Summary Data Q7:R8. Shows year-over-year revenue growth.
B14: Bar Chart (Retailer) | C14: Insert → Chart → Bar (horizontal). Data from Summary Data K7:L11. Compares retailer revenue.
B15: Pie Chart (Method) | C15: Insert → Chart → Pie. Data from Summary Data N7:O9. Shows In-store vs Online vs Outlet split.
... B17: Dark Theme | C17: All cells filled with dark hex colors (#1A1A2E background, #16213E cards) using PatternFill in openpyxl.
B19: KEY FORMULAS USED
B20: Total Sale Value | C20: =SUM('Nike Dataset'!G2:G25) -> 2025500
B21: By Region (SUMIF) | C21: SUMIF('Nike Dataset'!C2:C25, RegionName, 'Nike Dataset'!G2:G25)
B22: By Year (SUMPRODUCT) | C22: SUMPRODUCT((YEAR(DATEVALUE('Nike Dataset'!H2:H25))=Year)*'Nike Dataset'!G2:G25)
B23: Total Orders | C23: =COUNTA('Nike Dataset'!A2:A25) -> 24
